asgi_sitemaps/__init__.py
asgi_sitemaps/__version__.py
asgi_sitemaps/_app.py
asgi_sitemaps/_generation.py
asgi_sitemaps/_models.py
asgi_sitemaps/_types.py
asgi_sitemaps/py.typed
asgi_sitemaps-1.0.0.dist-info/LICENSE
asgi_sitemaps-1.0.0.dist-info/METADATA
asgi_sitemaps-1.0.0.dist-info/WHEEL
asgi_sitemaps-1.0.0.dist-info/top_level.txt
asgi_sitemaps-1.0.0.dist-info/RECORD
