Metadata-Version: 2.1
Name: asgi-sitemaps
Version: 1.0.0
Summary: Sitemap generation for ASGI applications.
Home-page: http://github.com/florimondmanca/asgi-sitemaps
Author: Florimond Manca
Author-email: florimond.manca@protonmail.com
License: MIT
Platform: UNKNOWN
Classifier: Development Status :: 5 - Production/Stable
Classifier: Intended Audience :: Developers
Classifier: Operating System :: OS Independent
Classifier: Framework :: AsyncIO
Classifier: Programming Language :: Python :: 3
Classifier: Programming Language :: Python :: 3 :: Only
Classifier: Programming Language :: Python :: 3.7
Classifier: Programming Language :: Python :: 3.8
Classifier: Programming Language :: Python :: 3.9
Classifier: Programming Language :: Python :: 3.10
Requires-Python: >=3.7
License-File: LICENSE
